ssprompt/__main__.py
ssprompt/__version__.py
ssprompt/console/__init__.py
ssprompt/console/application.py
ssprompt/console/command_loader.py
ssprompt/console/commands/__init__.py
ssprompt/console/commands/about.py
ssprompt/console/commands/add.py
ssprompt/console/commands/command.py
ssprompt/console/commands/init.py
ssprompt/console/commands/new.py
ssprompt/console/commands/pull.py
ssprompt/console/commands/show.py
ssprompt/console/commands/version.py
ssprompt/console/logging/__init__.py
ssprompt/console/logging/filters.py
ssprompt/console/logging/formatters/__init__.py
ssprompt/console/logging/formatters/formatter.py
ssprompt/console/logging/io_formatter.py
ssprompt/console/logging/io_handler.py
ssprompt/core/__init__.py
ssprompt/core/config/__init__.py
ssprompt/core/config/config.py
ssprompt/core/config/pyyaml.py
ssprompt/core/prompthub/__init__.py
ssprompt/core/prompthub/abstract_prompthub.py
ssprompt/core/prompthub/git_prompthub.py
ssprompt/core/vcs/__init__.py
ssprompt/core/vcs/git.py
ssprompt/layouts/__init__.py
ssprompt/layouts/layout.py
ssprompt/repositories/__init__.py
ssprompt/repositories/abstract_repository.py
ssprompt/repositories/pypi_repository.py
ssprompt/ssprompt.py
ssprompt/utils/__init__.py
ssprompt/utils/_compat.py
ssprompt-0.1.0.dist-info/LICENSE
ssprompt-0.1.0.dist-info/METADATA
ssprompt-0.1.0.dist-info/WHEEL
ssprompt-0.1.0.dist-info/entry_points.txt
ssprompt-0.1.0.dist-info/RECORD
