Metadata-Version: 2.1
Name: ssprompt
Version: 0.1.0
Summary: 
Author: chenfudong
Author-email: 260431910@qq.com
Requires-Python: >=3.10,<4.0
Classifier: Programming Language :: Python :: 3
Classifier: Programming Language :: Python :: 3.10
Classifier: Programming Language :: Python :: 3.11
Requires-Dist: cleo (>=2.0.1,<3.0.0)
Requires-Dist: importlib-metadata (==6.8.0)
Requires-Dist: packaging (==23.1)
Requires-Dist: pydantic (==1.10.12)
Requires-Dist: pyyaml (==6.0.1)
Requires-Dist: requests (>=2.31.0,<3.0.0)
Requires-Dist: tqdm (>=4.66.1,<5.0.0)
